vector3d/__init__.py
vector3d/point.py
vector3d/vector.py
vector3d-1.1.1.dist-info/LICENSE
vector3d-1.1.1.dist-info/METADATA
vector3d-1.1.1.dist-info/WHEEL
vector3d-1.1.1.dist-info/top_level.txt
vector3d-1.1.1.dist-info/RECORD
