Metadata-Version: 2.1
Name: vector3d
Version: 1.1.1
Summary: Vector3D is a small package for processing 3D vector in decartian system and some vector-related function, such as distance between two points, angle between vectors, ETC
Home-page: https://github.com/kirill-belousov/vector3d
Author: Cyrmax
Author-email: bkm.grotschool@yandex.ru
License: UNKNOWN
Platform: UNKNOWN
Classifier: Programming Language :: Python :: 3
Classifier: License :: OSI Approved :: MIT License
Classifier: Operating System :: OS Independent
